paspas/__init__.py
paspas/generator.py
paspas-0.0.3.data/scripts/paspas
paspas-0.0.3.dist-info/LICENSE
paspas-0.0.3.dist-info/METADATA
paspas-0.0.3.dist-info/WHEEL
paspas-0.0.3.dist-info/top_level.txt
paspas-0.0.3.dist-info/RECORD
