Metadata-Version: 2.1
Name: paspas
Version: 0.0.3
Summary: Simple password generator for CLI
Home-page: https://github.com/hirokikana/paspas
Author: Hiroki Takayasu
Author-email: hiroki.kana@gmail.com
License: MIT
Platform: UNKNOWN
Requires-Dist: pyyaml
